snapsht/__init__.py
snapsht/cli.py
snapsht-1.0.3.dist-info/LICENSE
snapsht-1.0.3.dist-info/METADATA
snapsht-1.0.3.dist-info/WHEEL
snapsht-1.0.3.dist-info/entry_points.txt
snapsht-1.0.3.dist-info/top_level.txt
snapsht-1.0.3.dist-info/RECORD
