Metadata-Version: 2.1
Name: snapsht
Version: 1.0.3
Summary: A command line application to capture full-page screenshots with ease, every time.
Home-page: https://github.com/raiyanyahya/snapsht
Author: Raiyan Yahya
Author-email: raiyanyahyadeveloper@gmail.com
License: MIT
Keywords: cli,developer tools,productivity,screenshot,python,selenium
Platform: UNKNOWN
Requires-Python: >3.5
Requires-Dist: click (==8.1.3)
Requires-Dist: rich (==13.3.2)
Requires-Dist: selenium (==4.8.2)
Requires-Dist: requests (==2.28.2)
